{
    "version": "Mothbot_yolo11m_4500_imgsz1600_b1_2024-01-18.pt",
    "flags": {},
    "imagePath": "D:\\MothboxData_Hubert\\data\\Panama\\Hoya_408m_calmoBarbo_2025-01-26\\2025-01-27\\calmoBarbo_2025_01_28__04_38_06_HDR0.jpg",
    "imageHeight": 6944,
    "imageWidth": 9248,
    "description": "",
    "imageData": null,
    "shapes": [
        {
            "kie_linking": [],
            "direction": 38.3560791015625,
            "label": "ORDER_Lepidoptera",
            "score": 0.8024175763130188,
            "group_id": null,
            "description": "",
            "difficult": "false",
            "shape_type": "rotation",
            "flags": {},
            "attributes": {},
            "points": [
                [
                    7570.6640625,
                    6682.6533203125
                ],
                [
                    8109.806640625,
                    6000.912109375
                ],
                [
                    7208.2216796875,
                    5287.91015625
                ],
                [
                    6669.0791015625,
                    5969.6513671875
                ]
            ],
            "patch_path": "patches/calmoBarbo_2025_01_28__04_38_06_HDR0_0_Mothbot_yolo11m_4500_imgsz1600_b1_2024-01-18.pt.jpg",
            "confidence_detection": 0.8024175763130188,
            "identifier_bot": "pybioclip_1.3.3",
            "identifier_human": "",
            "timestamp_detection": "2025-09-22__21_31_09_(+0200)",
            "detector_bot": "Mothbot_yolo11m_4500_imgsz1600_b1_2024-01-18.pt",
            "species_list": "https://doi.org/10.15468/dl.6nxkw6.csv",
            "timestamp_ID_bot": "2025-09-22__22_33_09_(+0200)",
            "confidence_ID": 0.990390956401825,
            "kingdom": "Animalia",
            "phylum": "Arthropoda",
            "class": "Insecta",
            "order": "Lepidoptera",
            "clusterID": 26.4,
            "timestamp_cluster": "2025-10-02__11_43_05_(+0200)"
        },
        {
            "kie_linking": [],
            "direction": 7.438676357269287,
            "label": "ORDER_Lepidoptera",
            "score": 0.7932320237159729,
            "group_id": null,
            "description": "",
            "difficult": "false",
            "shape_type": "rotation",
            "flags": {},
            "attributes": {},
            "points": [
                [
                    1526.190185546875,
                    3263.99609375
                ],
                [
                    1570.362060546875,
                    2926.94873046875
                ],
                [
                    1293.96044921875,
                    2890.724609375
                ],
                [
                    1249.78857421875,
                    3227.77197265625
                ]
            ],
            "patch_path": "patches/calmoBarbo_2025_01_28__04_38_06_HDR0_1_Mothbot_yolo11m_4500_imgsz1600_b1_2024-01-18.pt.jpg",
            "confidence_detection": 0.7932320237159729,
            "identifier_bot": "pybioclip_1.3.3",
            "identifier_human": "",
            "timestamp_detection": "2025-09-22__21_31_09_(+0200)",
            "detector_bot": "Mothbot_yolo11m_4500_imgsz1600_b1_2024-01-18.pt",
            "species_list": "https://doi.org/10.15468/dl.6nxkw6.csv",
            "timestamp_ID_bot": "2025-09-22__22_33_10_(+0200)",
            "confidence_ID": 0.985709011554718,
            "kingdom": "Animalia",
            "phylum": "Arthropoda",
            "class": "Insecta",
            "order": "Lepidoptera",
            "clusterID": 44.4,
            "timestamp_cluster": "2025-10-02__11_43_05_(+0200)"
        },
        {
            "kie_linking": [],
            "direction": 15.507874488830566,
            "label": "ORDER_Lepidoptera",
            "score": 0.778837263584137,
            "group_id": null,
            "description": "",
            "difficult": "false",
            "shape_type": "rotation",
            "flags": {},
            "attributes": {},
            "points": [
                [
                    6628.29296875,
                    1943.53076171875
                ],
                [
                    6729.048828125,
                    1580.3681640625
                ],
                [
                    6392.0673828125,
                    1486.875732421875
                ],
                [
                    6291.3115234375,
                    1850.038330078125
                ]
            ],
            "patch_path": "patches/calmoBarbo_2025_01_28__04_38_06_HDR0_2_Mothbot_yolo11m_4500_imgsz1600_b1_2024-01-18.pt.jpg",
            "confidence_detection": 0.778837263584137,
            "identifier_bot": "pybioclip_1.3.3",
            "identifier_human": "",
            "timestamp_detection": "2025-09-22__21_31_10_(+0200)",
            "detector_bot": "Mothbot_yolo11m_4500_imgsz1600_b1_2024-01-18.pt",
            "species_list": "https://doi.org/10.15468/dl.6nxkw6.csv",
            "timestamp_ID_bot": "2025-09-22__22_33_10_(+0200)",
            "confidence_ID": 0.9990060329437256,
            "kingdom": "Animalia",
            "phylum": "Arthropoda",
            "class": "Insecta",
            "order": "Lepidoptera",
            "clusterID": 69.3,
            "timestamp_cluster": "2025-10-02__11_43_05_(+0200)"
        },
        {
            "kie_linking": [],
            "direction": 56.063499450683594,
            "label": "ORDER_Lepidoptera",
            "score": 0.7626546025276184,
            "group_id": null,
            "description": "",
            "difficult": "false",
            "shape_type": "rotation",
            "flags": {},
            "attributes": {},
            "points": [
                [
                    7586.396484375,
                    3192.216796875
                ],
                [
                    7907.2861328125,
                    2976.681640625
                ],
                [
                    7600.8056640625,
                    2520.3916015625
                ],
                [
                    7279.916015625,
                    2735.9267578125
                ]
            ],
            "patch_path": "patches/calmoBarbo_2025_01_28__04_38_06_HDR0_3_Mothbot_yolo11m_4500_imgsz1600_b1_2024-01-18.pt.jpg",
            "confidence_detection": 0.7626546025276184,
            "identifier_bot": "pybioclip_1.3.3",
            "identifier_human": "",
            "timestamp_detection": "2025-09-22__21_31_10_(+0200)",
            "detector_bot": "Mothbot_yolo11m_4500_imgsz1600_b1_2024-01-18.pt",
            "species_list": "https://doi.org/10.15468/dl.6nxkw6.csv",
            "timestamp_ID_bot": "2025-09-22__22_33_10_(+0200)",
            "confidence_ID": 0.9990690350532532,
            "kingdom": "Animalia",
            "phylum": "Arthropoda",
            "class": "Insecta",
            "order": "Lepidoptera",
            "clusterID": 53.8,
            "timestamp_cluster": "2025-10-02__11_43_05_(+0200)"
        },
        {
            "kie_linking": [],
            "direction": 18.86358642578125,
            "label": "ORDER_Diptera",
            "score": 0.7468933463096619,
            "group_id": null,
            "description": "",
            "difficult": "false",
            "shape_type": "rotation",
            "flags": {},
            "attributes": {},
            "points": [
                [
                    6552.587890625,
                    4647.71484375
                ],
                [
                    6584.6796875,
                    4553.81640625
                ],
                [
                    6464.7216796875,
                    4512.818359375
                ],
                [
                    6432.6298828125,
                    4606.716796875
                ]
            ],
            "patch_path": "patches/calmoBarbo_2025_01_28__04_38_06_HDR0_4_Mothbot_yolo11m_4500_imgsz1600_b1_2024-01-18.pt.jpg",
            "confidence_detection": 0.7468933463096619,
            "identifier_bot": "pybioclip_1.3.3",
            "identifier_human": "",
            "timestamp_detection": "2025-09-22__21_31_11_(+0200)",
            "detector_bot": "Mothbot_yolo11m_4500_imgsz1600_b1_2024-01-18.pt",
            "species_list": "https://doi.org/10.15468/dl.6nxkw6.csv",
            "timestamp_ID_bot": "2025-09-22__22_33_11_(+0200)",
            "confidence_ID": 0.8417146801948547,
            "kingdom": "Animalia",
            "phylum": "Arthropoda",
            "class": "Insecta",
            "order": "Diptera",
            "clusterID": 218.82,
            "timestamp_cluster": "2025-10-02__11_43_05_(+0200)"
        },
        {
            "kie_linking": [],
            "direction": 11.797248840332031,
            "label": "ORDER_Lepidoptera",
            "score": 0.7100700736045837,
            "group_id": null,
            "description": "",
            "difficult": "false",
            "shape_type": "rotation",
            "flags": {},
            "attributes": {},
            "points": [
                [
                    1395.8343505859375,
                    2142.7041015625
                ],
                [
                    1448.3580322265625,
                    1891.922607421875
                ],
                [
                    1290.8392333984375,
                    1858.931884765625
                ],
                [
                    1238.3155517578125,
                    2109.71337890625
                ]
            ],
            "patch_path": "patches/calmoBarbo_2025_01_28__04_38_06_HDR0_5_Mothbot_yolo11m_4500_imgsz1600_b1_2024-01-18.pt.jpg",
            "confidence_detection": 0.7100700736045837,
            "identifier_bot": "pybioclip_1.3.3",
            "identifier_human": "",
            "timestamp_detection": "2025-09-22__21_31_11_(+0200)",
            "detector_bot": "Mothbot_yolo11m_4500_imgsz1600_b1_2024-01-18.pt",
            "species_list": "https://doi.org/10.15468/dl.6nxkw6.csv",
            "timestamp_ID_bot": "2025-09-22__22_33_11_(+0200)",
            "confidence_ID": 0.9927862286567688,
            "kingdom": "Animalia",
            "phylum": "Arthropoda",
            "class": "Insecta",
            "order": "Lepidoptera",
            "clusterID": 81.2,
            "timestamp_cluster": "2025-10-02__11_43_05_(+0200)"
        },
        {
            "kie_linking": [],
            "direction": 59.78868103027344,
            "label": "ORDER_Lepidoptera",
            "score": 0.6624009609222412,
            "group_id": null,
            "description": "",
            "difficult": "false",
            "shape_type": "rotation",
            "flags": {},
            "attributes": {},
            "points": [
                [
                    3682.8212890625,
                    2197.37060546875
                ],
                [
                    4235.88916015625,
                    1875.02734375
                ],
                [
                    3994.45556640625,
                    1460.78173828125
                ],
                [
                    3441.3876953125,
                    1783.125
                ]
            ],
            "patch_path": "patches/calmoBarbo_2025_01_28__04_38_06_HDR0_6_Mothbot_yolo11m_4500_imgsz1600_b1_2024-01-18.pt.jpg",
            "confidence_detection": 0.6624009609222412,
            "identifier_bot": "pybioclip_1.3.3",
            "identifier_human": "",
            "timestamp_detection": "2025-09-22__21_31_12_(+0200)",
            "detector_bot": "Mothbot_yolo11m_4500_imgsz1600_b1_2024-01-18.pt",
            "species_list": "https://doi.org/10.15468/dl.6nxkw6.csv",
            "timestamp_ID_bot": "2025-09-22__22_33_11_(+0200)",
            "confidence_ID": 0.9996239542961121,
            "kingdom": "Animalia",
            "phylum": "Arthropoda",
            "class": "Insecta",
            "order": "Lepidoptera",
            "clusterID": -1.0,
            "timestamp_cluster": "2025-10-02__11_43_05_(+0200)"
        },
        {
            "kie_linking": [],
            "direction": 82.64761352539062,
            "label": "ORDER_Diptera",
            "score": 0.6564902663230896,
            "group_id": null,
            "description": "",
            "difficult": "false",
            "shape_type": "rotation",
            "flags": {},
            "attributes": {},
            "points": [
                [
                    4672.2548828125,
                    3622.0302734375
                ],
                [
                    4764.9794921875,
                    3610.35107421875
                ],
                [
                    4751.650390625,
                    3504.52392578125
                ],
                [
                    4658.92578125,
                    3516.203125
                ]
            ],
            "patch_path": "patches/calmoBarbo_2025_01_28__04_38_06_HDR0_7_Mothbot_yolo11m_4500_imgsz1600_b1_2024-01-18.pt.jpg",
            "confidence_detection": 0.6564902663230896,
            "identifier_bot": "pybioclip_1.3.3",
            "identifier_human": "",
            "timestamp_detection": "2025-09-22__21_31_12_(+0200)",
            "detector_bot": "Mothbot_yolo11m_4500_imgsz1600_b1_2024-01-18.pt",
            "species_list": "https://doi.org/10.15468/dl.6nxkw6.csv",
            "timestamp_ID_bot": "2025-09-22__22_33_12_(+0200)",
            "confidence_ID": 0.7933042645454407,
            "kingdom": "Animalia",
            "phylum": "Arthropoda",
            "class": "Insecta",
            "order": "Diptera",
            "clusterID": -1.0,
            "timestamp_cluster": "2025-10-02__11_43_05_(+0200)"
        },
        {
            "kie_linking": [],
            "direction": 35.18873977661133,
            "label": "ORDER_Diptera",
            "score": 0.4621150493621826,
            "group_id": null,
            "description": "",
            "difficult": "false",
            "shape_type": "rotation",
            "flags": {},
            "attributes": {},
            "points": [
                [
                    5986.8984375,
                    3282.278564453125
                ],
                [
                    6042.302734375,
                    3204.612060546875
                ],
                [
                    5981.9580078125,
                    3161.565185546875
                ],
                [
                    5926.5537109375,
                    3239.231689453125
                ]
            ],
            "patch_path": "patches/calmoBarbo_2025_01_28__04_38_06_HDR0_8_Mothbot_yolo11m_4500_imgsz1600_b1_2024-01-18.pt.jpg",
            "confidence_detection": 0.4621150493621826,
            "identifier_bot": "pybioclip_1.3.3",
            "identifier_human": "",
            "timestamp_detection": "2025-09-22__21_31_13_(+0200)",
            "detector_bot": "Mothbot_yolo11m_4500_imgsz1600_b1_2024-01-18.pt",
            "species_list": "https://doi.org/10.15468/dl.6nxkw6.csv",
            "timestamp_ID_bot": "2025-09-22__22_33_12_(+0200)",
            "confidence_ID": 0.6483480334281921,
            "kingdom": "Animalia",
            "phylum": "Arthropoda",
            "class": "Insecta",
            "order": "Diptera",
            "clusterID": -1.0,
            "timestamp_cluster": "2025-10-02__11_43_05_(+0200)"
        }
    ],
    "filepath": "D:\\MothboxData_Hubert\\data\\Panama\\Hoya_408m_calmoBarbo_2025-01-26\\2025-01-27\\calmoBarbo_2025_01_28__04_38_06_HDR0.jpg",
    "uploaded": "",
    "sd": "",
    "device": "calmoBarbo",
    "firmware": "4.14",
    "sheet": "White felt / Fieltro blanco",
    "datasetcollection": "Panama",
    "project": "Hoya",
    "site": "408m",
    "longitude": "-80.77756",
    "latitude": "7.34419",
    "ground_height": 1.7,
    "deployment_name": "Panama_Hoya_408m_calmoBarbo_2025-01-26",
    "UTC": "-5",
    "deployment_date": "26/01/2025",
    "collect_date": "29/01/2025",
    "data_storage_location": "HDA and B",
    "crew": "HS, AQ, Bri",
    "notes": "408m elevation. 2nd battery added. Mature forest with evidence of selective logging. Ring lights stopped working on last night.",
    "schedule": "programA (19;21;23;2;4)",
    "habitat": "mature forest / bosque maduro",
    "attractor": "Mothbeam v2",
    "attractor_location": "internal - top of box"
}